koffer/__init__.py
koffer/cli.py
koffer/crypto.py
koffer/py.typed
koffer/storage.py
koffer/utils.py
koffer-0.1.1.dist-info/METADATA
koffer-0.1.1.dist-info/WHEEL
koffer-0.1.1.dist-info/entry_points.txt
koffer-0.1.1.dist-info/licenses/LICENSE
koffer-0.1.1.dist-info/RECORD
