Metadata-Version: 2.4
Name: koffer
Version: 0.1.1
Summary: Secure API key and token koffer with session-based unlock
Project-URL: Repository, https://github.com/jsnel/koffer
Author: koffer contributors
License: MIT
License-File: LICENSE
Keywords: api-keys,cli,encryption,koffer,secrets,security
Classifier: Development Status :: 4 - Beta
Classifier: Environment :: Console
Classifier: Intended Audience :: Developers
Classifier: License :: OSI Approved :: MIT License
Classifier: Operating System :: OS Independent
Classifier: Programming Language :: Python :: 3
Classifier: Programming Language :: Python :: 3.10
Classifier: Programming Language :: Python :: 3.11
Classifier: Programming Language :: Python :: 3.12
Classifier: Programming Language :: Python :: 3.13
Classifier: Programming Language :: Python :: 3.14
Classifier: Topic :: Security :: Cryptography
Classifier: Topic :: Utilities
Classifier: Typing :: Typed
Requires-Python: >=3.10
Requires-Dist: argon2-cffi>=23.1
Requires-Dist: cryptography>=42.0
Requires-Dist: keyring>=25.0
Requires-Dist: pyperclip>=1.8
Provides-Extra: dev
Requires-Dist: pre-commit>=3.2.0; extra == 'dev'
Requires-Dist: pytest-cov>=4.0; extra == 'dev'
Requires-Dist: pytest>=8.0; extra == 'dev'
Requires-Dist: ruff>=0.14.0; extra == 'dev'
